async_firebase/__init__.py
async_firebase/_config.py
async_firebase/base.py
async_firebase/client.py
async_firebase/encoders.py
async_firebase/errors.py
async_firebase/messages.py
async_firebase/utils.py
async_firebase-4.1.0.dist-info/LICENSE
async_firebase-4.1.0.dist-info/METADATA
async_firebase-4.1.0.dist-info/WHEEL
async_firebase-4.1.0.dist-info/RECORD
