Metadata-Version: 2.1
Name: async-firebase
Version: 4.1.0
Summary: Async Firebase Client - a Python asyncio client to interact with Firebase Cloud Messaging in an easy way.
Home-page: https://github.com/healthjoy/async-firebase
License: MIT
Keywords: async,asyncio,firebase,fcm,python3,push-notifications
Author: Oleksandr Omyshev
Author-email: oomyshev@healthjoy.com
Maintainer: Healthjoy Developers
Maintainer-email: developers@healthjoy.com
Requires-Python: >=3.9,<3.14
Classifier: Development Status :: 5 - Production/Stable
Classifier: Intended Audience :: Developers
Classifier: License :: OSI Approved :: MIT License
Classifier: Natural Language :: English
Classifier: Programming Language :: Python :: 3
Classifier: Programming Language :: Python :: 3.9
Classifier: Programming Language :: Python :: 3.10
Classifier: Programming Language :: Python :: 3.11
Classifier: Programming Language :: Python :: 3 :: Only
Classifier: Programming Language :: Python :: 3.12
Classifier: Programming Language :: Python :: 3.13
Requires-Dist: google-auth (>=2.38.0,<2.39.0)
Requires-Dist: h11 (>=0.16.0)
Requires-Dist: httpx[http2] (>=0.28.1,<1.0.0)
Project-URL: Repository, https://github.com/healthjoy/async-firebase
